{
  "fixtures": [
    {
      "id": "eb93",
      "match_id": "206566",
      "country_id": "44",
      "league_name": "Premier League",
      "match_date": "2024-03-09",
      "match_status": "Finished",
      "match_time": "16:00",
      "match_hometeam_id": "3071",
      "match_hometeam_name": "Bournemouth",
      "match_hometeam_score": "2",
      "match_awayteam_id": "3074",
      "match_awayteam_name": "Sheffield Utd",
      "match_awayteam_score": "2"
    },
    {
      "id": "0a62",
      "match_id": "206567",
      "country_id": "44",
      "league_name": "Premier League",
      "match_date": "2024-03-09",
      "match_status": "Finished",
      "match_time": "18:30",
      "match_hometeam_id": "141",
      "match_hometeam_name": "Arsenal",
      "match_hometeam_score": "2",
      "match_awayteam_id": "3086",
      "match_awayteam_name": "Brentford",
      "match_awayteam_score": "1"
    },
    {
      "id": "dbb4",
      "match_id": "206571",
      "country_id": "44",
      "league_name": "Premier League",
      "match_date": "2024-03-09",
      "match_status": "Finished",
      "match_time": "16:00",
      "match_hometeam_id": "3429",
      "match_hometeam_name": "Crystal Palace",
      "match_hometeam_score": "1",
      "match_awayteam_id": "3091",
      "match_awayteam_name": "Luton",
      "match_awayteam_score": "1"
    },
    {
      "id": "9ef4",
      "match_id": "206573",
      "country_id": "44",
      "league_name": "Premier League",
      "match_date": "2024-03-09",
      "match_status": "",
      "match_time": "13:30",
      "match_hometeam_id": "102",
      "match_hometeam_name": "Manchester Utd",
      "match_hometeam_score": "",
      "match_awayteam_id": "3073",
      "match_awayteam_name": "Everton",
      "match_awayteam_score": ""
    },
    {
      "id": "6682",
      "match_id": "206575",
      "country_id": "44",
      "league_name": "Premier League",
      "match_date": "2024-03-09",
      "match_status": "",
      "match_time": "16:00",
      "match_hometeam_id": "3077",
      "match_hometeam_name": "Wolves",
      "match_hometeam_score": "",
      "match_awayteam_id": "3085",
      "match_awayteam_name": "Fulham",
      "match_awayteam_score": ""
    },
    {
      "id": "f1b0",
      "match_id": "206568",
      "country_id": "44",
      "league_name": "Premier League",
      "match_date": "2024-03-10",
      "match_status": "",
      "match_time": "14:00",
      "match_hometeam_id": "3088",
      "match_hometeam_name": "Aston Villa",
      "match_hometeam_score": "",
      "match_awayteam_id": "164",
      "match_awayteam_name": "Tottenham",
      "match_awayteam_score": ""
    },
    {
      "id": "19ab",
      "match_id": "206569",
      "country_id": "44",
      "league_name": "Premier League",
      "match_date": "2024-03-10",
      "match_status": "",
      "match_time": "15:00",
      "match_hometeam_id": "3079",
      "match_hometeam_name": "Brighton",
      "match_hometeam_score": "",
      "match_awayteam_id": "3089",
      "match_awayteam_name": "Nottingham",
      "match_awayteam_score": ""
    },
    {
      "id": "3f12",
      "match_id": "206572",
      "country_id": "44",
      "league_name": "Premier League",
      "match_date": "2024-03-10",
      "match_status": "",
      "match_time": "16:45",
      "match_hometeam_id": "84",
      "match_hometeam_name": "Liverpool",
      "match_hometeam_score": "",
      "match_awayteam_id": "80",
      "match_awayteam_name": "Manchester City",
      "match_awayteam_score": ""
    },
    {
      "id": "6c89",
      "match_id": "206574",
      "country_id": "44",
      "league_name": "Premier League",
      "match_date": "2024-03-10",
      "match_status": "",
      "match_time": "15:00",
      "match_hometeam_id": "3081",
      "match_hometeam_name": "West Ham",
      "match_hometeam_score": "",
      "match_awayteam_id": "3075",
      "match_awayteam_name": "Burnley",
      "match_awayteam_score": ""
    },
    {
      "id": "8acc",
      "match_id": "206570",
      "country_id": "44",
      "league_name": "Premier League",
      "match_date": "2024-03-11",
      "match_status": "",
      "match_time": "21:00",
      "match_hometeam_id": "88",
      "match_hometeam_name": "Chelsea",
      "match_hometeam_score": "",
      "match_awayteam_id": "3100",
      "match_awayteam_name": "Newcastle",
      "match_awayteam_score": ""
    },
    {
      "id": "d5a1",
      "match_id": "206456",
      "country_id": "44",
      "league_name": "Premier League",
      "match_date": "2024-03-13",
      "match_status": "",
      "match_time": "20:30",
      "match_hometeam_id": "3071",
      "match_hometeam_name": "Bournemouth",
      "match_hometeam_score": "",
      "match_awayteam_id": "3091",
      "match_awayteam_name": "Luton",
      "match_awayteam_score": ""
    }
  ],
  "users": [
    {
      "id": "RidfVBiIj3k5DLoWIogj2w==",
      "name": "Linn Htet",
      "avatar": "https://media-direct.cdn.viber.com/download_photo?dlid=3FHQOeDmJzQ2GURSH2eINyLLQzlL_w7HhJbxL3P4gZGuYTnT_XUvEnxns-czryyhZo0XY1iJbWuIc2GogTEurU3RkvW94Pf1EBBQRtV5Ttzo_yVhxarRW86tdl69pSK9NppkHg&fltp=jpg&imsz=0000",
      "country": "MM",
      "language": "en",
      "scores": 4
    }
  ],
  "user-prediction-histories": [
    {
      "id": "1",
      "user_id": "RidfVBiIj3k5DLoWIogj2w==",
      "match_id": "206566",
      "win_lose": "Lose",
      "date": "2024-03-08",
      "predict": "W1",
      "match_finished": true
    },
    {
      "id": "2",
      "user_id": "RidfVBiIj3k5DLoWIogj2w==",
      "match_id": "206567",
      "win_lose": "Win",
      "date": "2024-03-08",
      "predict": "W1",
      "match_finished": true
    },
    {
      "id": "3",
      "user_id": "RidfVBiIj3k5DLoWIogj2w==",
      "match_id": "206571",
      "win_lose": "Win",
      "date": "2024-03-08",
      "predict": "Draw",
      "match_finished": true
    }
  ]
}